pypi_mirror.py
python_pypi_mirror-5.2.1.dist-info/LICENSE
python_pypi_mirror-5.2.1.dist-info/METADATA
python_pypi_mirror-5.2.1.dist-info/WHEEL
python_pypi_mirror-5.2.1.dist-info/entry_points.txt
python_pypi_mirror-5.2.1.dist-info/top_level.txt
python_pypi_mirror-5.2.1.dist-info/RECORD
