Metadata-Version: 2.1
Name: python-pypi-mirror
Version: 5.2.1
Summary: A script to create a partial PyPI mirror
Home-page: https://github.com/montag451/pypi-mirror
Author: montag451
Author-email: montag451@laposte.net
Maintainer: montag451
Maintainer-email: montag451@laposte.net
Classifier: Programming Language :: Python
Classifier: Programming Language :: Python :: 3
Classifier: Programming Language :: Python :: 3 :: Only
Classifier: Programming Language :: Python :: 3.7
Classifier: Programming Language :: Python :: 3.8
Classifier: Programming Language :: Python :: 3.9
Classifier: Programming Language :: Python :: 3.10
Classifier: Programming Language :: Python :: 3.11
Classifier: Programming Language :: Python :: 3.12
Requires-Python: >=3.7
License-File: LICENSE
